DataPreprocessingAnalytics4all4ever/__init__.py
DataPreprocessing4Analytics-2023.0.3.dist-info/LICENSE.txt.txt
DataPreprocessing4Analytics-2023.0.3.dist-info/METADATA
DataPreprocessing4Analytics-2023.0.3.dist-info/WHEEL
DataPreprocessing4Analytics-2023.0.3.dist-info/top_level.txt
DataPreprocessing4Analytics-2023.0.3.dist-info/RECORD
